{
  "version": "0.2",
  "language": "en",
  "words": [
    "azordev",
    "Laguan",
    "linkedin",
    "autenticación",
    "Azócar",
    "azordev",
    "commitlint",
    "coolticket",
    "Descomenta",
    "dockerignore",
    "emmanuel",
    "enrutar",
    "eslintignore",
    "expressjs",
    "inicialización",
    "interation",
    "Laguan",
    "linkedin",
    "maxsize",
    "micropayment",
    "middlewares",
    "npmrc",
    "nvmrc",
    "oneliners",
    "ormconfig",
    "pgweb",
    "portabilidad",
    "postgres",
    "psql",
    "sepáralas",
    "signup",
    "tabulación",
    "Tabulaciones",
    "typeorm",
    "urlencode",
    "validador",
    "wiston"
  ],
  "flagWords": [
    "hte"
  ],
  "ignorePaths": [
    "./.github/**",
    "./.vscode/**",
    "./.build/**",
    "node_modules/**",
    "package.json",
    "package-lock.json",
    "*ignore",
    ".*rc",
    "**",
    "docker-compose.yml",
    "docker-compose-*.yml",
    "Dockerfile",
    "Dockerfile.*",
    "ormconfig.j"
  ],
  "import": [
    "@cspell/dict-es-es/cspell-ext.json"
  ]
}
